COPYING
COPYING.LESSER
MANIFEST.in
README.txt
ez_setup.py
setup.py
lancelot/__init__.py
lancelot/calling.py
lancelot/comparators.py
lancelot/constraints.py
lancelot/specification.py
lancelot/verification.py
lancelot.egg-info/PKG-INFO
lancelot.egg-info/SOURCES.txt
lancelot.egg-info/dependency_links.txt
lancelot.egg-info/top_level.txt
lancelot/examples/__init__.py
lancelot/examples/additional_comparators.py
lancelot/examples/fibonacci_spec.py
lancelot/examples/observer_spec.py
lancelot/examples/stack_spec.py
lancelot/specs/__init__.py
lancelot/specs/calling_spec.py
lancelot/specs/comparator_spec.py
lancelot/specs/constraint_spec.py
lancelot/specs/mocking_spec.py
lancelot/specs/simple_fns.py
lancelot/specs/specification_spec.py
lancelot/specs/verification_spec.py